dslibrary/__init__.py
dslibrary/engine_intf.py
dslibrary/engines.py
dslibrary/exceptions.py
dslibrary/front.py
dslibrary/metadata.py
dslibrary/proto_handlers.py
dslibrary/run_models.py
dslibrary/to_local.py
dslibrary/sql/__init__.py
dslibrary/sql/compiled.py
dslibrary/sql/compiler.py
dslibrary/sql/data.py
dslibrary/sql/data_to_sql.py
dslibrary/sql/df_iterator.py
dslibrary/sql/eval_utils.py
dslibrary/sql/exceptions.py
dslibrary/sql/expr_analysis.py
dslibrary/sql/file_sql.py
dslibrary/sql/file_sql_wr.py
dslibrary/sql/misc.py
dslibrary/sql/modify_sql.py
dslibrary/sql/parser.py
dslibrary/sql/q_pandas.py
dslibrary/sql/s2p_errs.py
dslibrary/sql/select_stmt.py
dslibrary/sql/sql_to_pandas.py
dslibrary/sql/statements.py
dslibrary/sql/streaming_query.py
dslibrary/sql/streams.py
dslibrary/sql/tokenize.py
dslibrary/transport/__init__.py
dslibrary/transport/http_to_dsl.py
dslibrary/transport/sample_rest.py
dslibrary/transport/to_local.py
dslibrary/transport/to_mmlibrary.py
dslibrary/transport/to_rest.py
dslibrary/transport/to_volume.py
dslibrary/transport/volume_watcher.py
dslibrary/utils/__init__.py
dslibrary/utils/bigq.py
dslibrary/utils/connect.py
dslibrary/utils/csp_connect.py
dslibrary/utils/dbconn.py
dslibrary/utils/df_utils.py
dslibrary/utils/file_utils.py
dslibrary/utils/filechunker.py
dslibrary/utils/folder_db.py
dslibrary/utils/format_sniffer.py
dslibrary/utils/instantiation.py
dslibrary/utils/nosql.py
dslibrary/utils/packages.py
dslibrary/utils/preview.py
dslibrary-0.0.74.dist-info/METADATA
dslibrary-0.0.74.dist-info/WHEEL
dslibrary-0.0.74.dist-info/top_level.txt
dslibrary-0.0.74.dist-info/RECORD
