Metadata-Version: 2.1
Name: dslibrary
Version: 0.0.74
Summary: Data Science Framework & Abstractions
Home-page: UNKNOWN
License: Apache
Platform: UNKNOWN
Classifier: License :: OSI Approved :: Apache Software License
Classifier: Programming Language :: Python :: 3
Requires-Dist: jsonschema
Requires-Dist: pyyaml
Requires-Dist: pandas
Requires-Dist: pexpect
Provides-Extra: all
Requires-Dist: fsspec ; extra == 'all'
Requires-Dist: boto3 ; extra == 'all'
Requires-Dist: s3fs ; extra == 'all'
Requires-Dist: gcsfs ; extra == 'all'
Requires-Dist: adlfs ; extra == 'all'
Requires-Dist: psycopg2-binary ; extra == 'all'
Requires-Dist: PyMySQL ; extra == 'all'
Requires-Dist: sqlite3 ; extra == 'all'
Requires-Dist: openpyxl ; extra == 'all'
